emulator/__init__.py
emulator/args.py
emulator/em_object.py
emulator/keys.py
emulator/node.py
emulator/opencv.py
emulator/option.py
emulator/adb/AdbWinApi.dll
emulator/adb/AdbWinUsbApi.dll
emulator/adb/adb.exe
emulator/base64/base64.exe
emulator/dump/window_dump.xml
emulator/sed/libiconv2.dll
emulator/sed/libintl3.dll
emulator/sed/regex2.dll
emulator/sed/sed.exe
emulator_Thw-0.0.11.dist-info/LICENSE.txt
emulator_Thw-0.0.11.dist-info/METADATA
emulator_Thw-0.0.11.dist-info/WHEEL
emulator_Thw-0.0.11.dist-info/top_level.txt
emulator_Thw-0.0.11.dist-info/RECORD
